sugar/__init__.py
sugar/__main__.py
sugar/cli.py
sugar/console.py
sugar/core.py
sugar/docs.py
sugar/extensions/__init__.py
sugar/extensions/base.py
sugar/extensions/compose.py
sugar/extensions/compose_ext.py
sugar/extensions/podman_ext.py
sugar/extensions/stats.py
sugar/extensions/swarm.py
sugar/extensions/tui.py
sugar/inspect.py
sugar/logs.py
sugar/schema.json
sugar/tui/__init__.py
sugar/tui/app.py
sugar/tui/data/app.json
sugar/tui/screens/__init__.py
sugar/tui/screens/details.py
sugar/tui/screens/logs.py
sugar/tui/screens/profiles.py
sugar/tui/screens/services.py
sugar/tui/styles/screens.css
sugar/tui/styles/styles.css
sugar/utils.py
sugar/validation.py
containers_sugar-1.19.2.dist-info/LICENSE
containers_sugar-1.19.2.dist-info/METADATA
containers_sugar-1.19.2.dist-info/WHEEL
containers_sugar-1.19.2.dist-info/entry_points.txt
containers_sugar-1.19.2.dist-info/RECORD
