Metadata-Version: 2.3
Name: containers-sugar
Version: 1.19.2
Summary: Simplify the usage of containers
License: BSD 3 Clause
Author: Ivan Ogasawara
Author-email: ivan.ogasawara@gmail.com
Requires-Python: >=3.9,<4
Classifier: License :: Other/Proprietary License
Classifier: Programming Language :: Python :: 3
Classifier: Programming Language :: Python :: 3.9
Classifier: Programming Language :: Python :: 3.10
Classifier: Programming Language :: Python :: 3.11
Classifier: Programming Language :: Python :: 3.12
Classifier: Programming Language :: Python :: 3.13
Provides-Extra: tui
Requires-Dist: Jinja2 (>=2)
Requires-Dist: colorama (>=0.4.6)
Requires-Dist: compose-go (>=1.27.0)
Requires-Dist: jsonschema (>=4)
Requires-Dist: plotille (>=5) ; extra == "tui"
Requires-Dist: podman-compose (>=1.3.0,<2.0.0)
Requires-Dist: python-dotenv (>=0.21.1)
Requires-Dist: pyyaml (>=6)
Requires-Dist: rich (>=10.11.0) ; extra == "tui"
Requires-Dist: sh (>=2.0.0)
Requires-Dist: textual (>=0.48) ; extra == "tui"
Requires-Dist: typer (>=0.9.0)
Requires-Dist: xonsh (>=0.15.0)
